{"content":{"title":"рж╕ржирзНрждрж╛ржирзЗрж░ рж╢рзЗржЦрж╛рж░ рж╕ржмржЪрзЗрзЯрзЗ ржмрзЬ ржмрж╛ржзрж╛ ржХрзА?","subtitle":"ржоржирзЛржпрзЛржЧ, ржмрж┐рж░ржХрзНрждрж┐ ржирж╛ржХрж┐ ржоржирзЗ ржирж╛ ржерж╛ржХрж╛?","image":"https://raw.githubusercontent.com/qwer87asdf/lI0IlolI-km/refs/heads/master/notification/image/kids-course-30-aug.jpg","body":"<p>ржЖржЬржХрзЗрж░ ржбрж┐ржЬрж┐ржЯрж╛рж▓ ржпрзБржЧрзЗ ржЕржирзЗржХ ржмрж╛ржмрж╛-ржорж╛ ржЕржнрж┐ржпрзЛржЧ ржХрж░рзЗржитАФтАЬ<strong>ржЖржорж╛рж░ рж╕ржирзНрждрж╛ржи ржкрзЬрждрзЗ ржмрж╕рж▓рзЗ ржоржирзЛржпрзЛржЧ ржзрж░рзЗ рж░рж╛ржЦрждрзЗ ржкрж╛рж░рзЗ ржирж╛, ржжрзНрж░рзБржд ржмрж┐рж░ржХрзНржд рж╣рзЯрзЗ ржпрж╛рзЯ, ржЖржмрж╛рж░ рж╢рзЗржЦрж╛ ржЬрж┐ржирж┐рж╕ржУ ржмрзЗрж╢рж┐ржХрзНрж╖ржг ржоржирзЗ ржерж╛ржХрзЗ ржирж╛ред</strong>тАЭ ржЧржмрзЗрж╖ржгрж╛рзЯ ржжрзЗржЦрж╛ ржЧрзЗржЫрзЗ, ржПржЗ рж╕ржмржЧрзБрж▓рзЛржЗ ржПржХрзЗ ржЕржкрж░рзЗрж░ рж╕рж╛ржерзЗ ржЧржнрзАрж░ржнрж╛ржмрзЗ ржпрзБржХрзНржд ржПржмржВ рж╕ржирзНрждрж╛ржирзЗрж░ рж╢рзЗржЦрж╛рж░ ржкржерзЗ ржмрзЬ ржмрж╛ржзрж╛ рж╣рзЯрзЗ ржжрж╛ржБрзЬрж╛рзЯред</p><p>ржоржирзЛржпрзЛржЧ ржирж╛ ржерж╛ржХрж▓рзЗ ржЗржиржлрж░ржорзЗрж╢ржи рж╕ржарж┐ржХржнрж╛ржмрзЗ ржмрзНрж░рзЗржЗржирзЗ ржкрзНрж░ржмрзЗрж╢ржЗ ржХрж░рзЗ ржирж╛, ржлрж▓рзЗ рждрж╛ рж╕рзНржорзГрждрж┐рждрзЗ ржмрзЗрж╢рж┐ржХрзНрж╖ржг ржерж╛ржХрзЗ ржирж╛ред ржЖржмрж╛рж░ ржоржирзЛржпрзЛржЧ рж╣рж╛рж░рж┐рзЯрзЗ ржЧрзЗрж▓рзЗ рж╢рж┐рж╢рзБ ржжрзНрж░рзБржд ржмрж┐рж░ржХрзНржд рж╣рзЯрзЗ ржпрж╛рзЯ, ржкрзЬрж╛рж╢рзЛржирж╛ржХрзЗ ржмрж┐рж░ржХрзНрждрж┐ржХрж░ ржоржирзЗ ржХрж░рзЗ ржПржмржВ рж╢рзЗржЦрж╛рж░ ржЖржЧрзНрж░рж╣ржУ рж╣рж╛рж░рж┐рзЯрзЗ ржлрзЗрж▓рзЗред<em><small> </small></em></p><p>рж╢рж┐рж╢рзБрж░ рж╢рзЗржЦрж╛рж░ рж╕ржмржЪрзЗржпрж╝рзЗ ржкрзНрж░ржнрж╛ржмрж╢рж╛рж▓рзА ржЙржкрж╛ржпрж╝ржЧрзБрж▓рзЛрж░ ржПржХржЯрж┐ рж╣рж▓рзЛ ржЧрж▓рзНржк ржмрж▓рж╛рж░ ржорж╛ржзрзНржпржорзЗ рж╢рзЗржЦрж╛ржирзЛред ржПржЯрж┐ ржЬрзНржЮрж╛ржирж╛рж░рзНржЬржирзЗрж░ ржкрж╛рж╢рж╛ржкрж╛рж╢рж┐ ржЖржмрзЗржЧ, ржХрж▓рзНржкржирж╛, ржнрж╛рж╖рж╛ ржПржмржВ рж╕рж╛ржорж╛ржЬрж┐ржХ ржжржХрзНрж╖рждрж╛рж░ рж╕рж╛ржерзЗ рж╢рзЗржЦрж╛рж░ ржЧржнрзАрж░ рж╕ржорзНржкрж░рзНржХ ржЧржбрж╝рзЗ рждрзЛрж▓рзЗред</p><p>ржЧржмрзЗрж╖ржгрж╛ржпрж╝ ржжрзЗржЦрж╛ ржЧрзЗржЫрзЗ, <strong>ржЧрж▓рзНржк ржмрж▓рж╛рж░ ржорж╛ржзрзНржпржорзЗ рж╢рж┐рж╢рзБржжрзЗрж░ ржХрж▓рзНржкржирж╛рж╢ржХрзНрждрж┐ ржУ ржнрж╛рж╖рж╛ ржжржХрзНрж╖рждрж╛ ржмрзГржжрзНржзрж┐ ржкрж╛ржпрж╝ ржПржмржВ рж╢ржмрзНржжржнрж╛ржирзНржбрж╛рж░ рж╕ржорзГржжрзНржз рж╣ржпрж╝ред </strong><em><small>(Nagasundaram et al., 2018, p.2) </small></em><strong>ржЧрж▓рзНржк рж╢рзЗржЦрж╛рж░ ржкрзНрж░ржХрзНрж░рж┐ржпрж╝рж╛ржХрзЗ ржЖржмрзЗржЧрзЗрж░ рж╕рж╛ржерзЗ ржпрзБржХрзНржд ржХрж░рзЗ, ржпрж╛ рж╢рзЗржЦрж╛ржХрзЗ ржЖрж░ржУ ржЧржнрзАрж░ ржУ рж╕рзНржорж░ржгрзАржпрж╝ ржХрж░рзЗ рждрзЛрж▓рзЗред</strong> <em><small>(Pezzullo, 2020, p.4)</small></em> ржПржХржЗрж╕рж╛ржерзЗ, <strong>ржЧрж▓рзНржкрзЗрж░ ржорж╛ржзрзНржпржорзЗ рж╢рж┐рж╢рзБржжрзЗрж░ рж╕рж╣рж╛ржирзБржнрзВрждрж┐, рж╕рж╛ржорж╛ржЬрж┐ржХ ржорзВрж▓рзНржпржмрзЛржз ржУ ржирзИрждрж┐ржХрждрж╛ ржмрж┐ржХрж╢рж┐ржд рж╣ржпрж╝ред</strong>  <em><small>(Utami et al., 2022, p.3)</small></em></p><p>рж╢рзБржзрзБ рждрж╛ржЗ ржиржпрж╝, ржбрж┐ржЬрж┐ржЯрж╛рж▓ ржЧрж▓рзНржкрзЗрж░ ржорж╛ржзрзНржпржорзЗ рж╢рзЗржЦрж╛ржирзЛржУ ржЕржирж▓рж╛ржЗржи рж╢рж┐ржХрзНрж╖рж╛ржпрж╝ рж╢рж┐рж╢рзБржжрзЗрж░ ржЙржжрзНржмрзЗржЧ ржХржорж╛рждрзЗ ржХрж╛рж░рзНржпржХрж░ ржкрзНрж░ржорж╛ржгрж┐ржд рж╣ржпрж╝рзЗржЫрзЗред <em><small>(Al-kindi Publisher, 2024; Online Learning Journal, 2024)</small></em></p><p>ржХрж╛рж╣ржл ржХрж┐ржбрж╕рзЗ тАЬ<strong>ржЧрж▓рзНржкрзЗ ржЧрж▓рзНржкрзЗ рж╢рж┐рж╢рзБ-ржХрж┐рж╢рзЛрж░ржжрзЗрж░ ржЗрж╕рж▓рж╛ржо рж╢рж┐ржХрзНрж╖рж╛</strong>тАЭ ржкрзНрж░рзЛржЧрзНрж░рж╛ржорзЗ ржПржЗ ржЪрзНржпрж╛рж▓рзЗржЮрзНржЬржЧрзБрж▓рзЛ ржорж╛ржерж╛рзЯ рж░рзЗржЦрзЗ ржХрзНрж▓рж╛рж╕ рж╕рж╛ржЬрж╛ржирзЛ рж╣рзЯрзЗржЫрзЗред</p><ul><li><p>ржПржХрзНрж╕ржкрж╛рж░рзНржЯ ржЯрж┐ржЪрж╛рж░ржжрзЗрж░ ржорж╛ржзрзНржпржорзЗ ржЗржирзНржЯрж╛рж░рзЗржХрзНржЯрж┐ржн ржХрзНрж▓рж╛рж╕</p></li><li><p>ржЧрж▓рзНржк, ржнрж┐ржЬрзНржпрзБрзЯрж╛рж▓, ржХрзБржЗржЬ, ржПрж╕рж╛ржЗржиржорзЗржирзНржЯ ржЖрж░ ржПржХрзНржЯрж┐ржнрж┐ржЯрж┐рж░ ржорж╛ржзрзНржпржорзЗ рж╢рзЗржЦрж╛ржирзЛ</p></li></ul><p>ЁЯСЙ ржЖржкржирж┐ ржЪрж╛ржЗрж▓рзЗ ржЖржкржирж╛рж░ рж╕ржирзНрждрж╛ржирзЗрж░ ржЬржирзНржп ржПржХржЯрж┐ ржлрзНрж░рж┐ ржбрзЗржорзЛ ржХрзНрж▓рж╛рж╕рзЗ ржЕржВрж╢ ржирж┐рзЯрзЗ рж╕рж░рж╛рж╕рж░рж┐ ржПржЗ ржЕржнрж┐ржЬрзНржЮрждрж╛ ржирж┐рждрзЗ ржкрж╛рж░рзЗржиред ржбрзЗржорзЛ ржХрзНрж▓рж╛рж╕рзЗ ржЬрзЯрзЗржи ржХрж░рждрзЗ рж░рзЗржЬрж┐рж╕рзНржЯрзНрж░рзЗрж╢ржи ржХрж░рзЗ ржлрзЗрж▓рзБржи ржжрзНрж░рзБрждред рж░рзЗржЬрж┐рж╕рзНржЯрзНрж░рзЗрж╢ржи рж▓рж┐ржЩрзНржХ: <a href=\"https://forms.gle/SFmPdVnWHA3mhEy37\">https://forms.gle/SFmPdVnWHA3mhEy37</a></p>"},"reference":[],"footer_button":{"hint":"","text":"","link":""}}