{"content":{"title":"The First Pledge of Aqabah","subtitle":"A secret midnight meeting in the valley of Aqabah became the first spark that illuminated ","image":"https://raw.githubusercontent.com/qwer87asdf/lI0IlolI-km/master/notification/image/convertedimage-6a0b25062257b.jpg","body":"<p>Through the suffocating darkness of Makkah, a miraculous light quietly emerged within the narrow valley of Aqabah. During the crowded season of Hajj, twelve young men from Yathrib (Madinah) secretly crossed the mountain paths under the cover of night, escaping the watchful eyes of Quraysh. Exhausted by tribal wars, bloodshed, and the emptiness of Jahiliyyah, their hearts longed for truth.</p><p>There, in the silence of the night, they met Muhammad, the Messenger of Allah ﷺ. As he recited the powerful verses of the Qur’an, the message of Tawhid shook their souls and shattered the darkness of idol worship that had ruled Arabia for centuries.</p><p>That night, they pledged their hands to the Prophet ﷺ in what history remembers as <em>The First Pledge of Aqabah</em> — not a political alliance, but a covenant of faith, morality, and spiritual rebirth.</p><p>They vowed:</p><ul><li><p>To worship Allah alone,</p></li><li><p>To abandon theft and immorality,</p></li><li><p>To never kill their children out of poverty,</p></li><li><p>To avoid false accusations,</p></li><li><p>And to obey the Prophet ﷺ in every righteous matter.</p></li></ul><p>While Makkah slept in silence, a new chapter of history was being written in Aqabah — a moment that would soon bring the first dawn of iman to Madinah and transform the course of the world forever.</p><h2>References</h2><ul><li><p>Sahih al-Bukhari — Hadith 3999</p></li><li><p>Sahih Muslim — Hadith 1709</p></li><li><p>Sirat Ibn Hisham</p></li><li><p>Ar-Raheeq Al-Makhtum</p></li></ul>"},"reference":[],"footer_button":{"hint":"","text":"","link":""}}