[
  {
    "name": "about_us",
    "url": "appdata/data/{lang}/about_us.json",
    "updated_at": 1767498887000
  },
  {
    "name": "change_log",
    "url": "appdata/data/{lang}/change_log.json",
    "updated_at": 1759452289367
  },
  {
    "name": "ifa_times",
    "url": "appdata/data/ifa_times.json",
    "updated_at": 1772407196000
  },
  {
    "name": "hijri_date",
    "url": "appdata/data/hijri_date.json",
    "updated_at": 1759452289367
  },
  {
    "name": "salat_reference",
    "url": "appdata/data/{lang}/salat_reference.json",
    "updated_at": 1770949104584
  },
  {
    "name": "prohibited_time_reference",
    "url": "appdata/data/{lang}/prohibited_time_reference.json",
    "updated_at": 1759452289367
  },
  {
    "name": "daily_notification",
    "url": "appdata/data/{lang}/daily_notification.json",
    "updated_at": 1759452289367
  },
  {
    "name": "event_animations",
    "url": "appdata/data/event_animations.json",
    "updated_at": 1759452289367
  },
  {
    "name": "dua",
    "url": "appdata/data/{lang}/dua.json",
    "updated_at": 1773013355000
  },
  {
    "name": "selected_quran",
    "url": "appdata/data/{lang}/selected_quran.json",
    "updated_at": 1759452289367
  },
  {
    "name": "selected_hadith",
    "url": "appdata/data/{lang}/selected_hadith.json",
    "updated_at": 1759452289367
  },
  {
    "name": "asmaul_husna",
    "url": "appdata/data/{lang}/asmaul_husna.json",
    "updated_at": 1769387983000
  },
  {
    "name": "settings",
    "url": "appdata/data/settings.json",
    "updated_at": 1771500505000
  },
  {
    "name": "hijri_date_v2",
    "url": "appdata/data/hijri_date/{code}_hijri_date.json",
    "updated_at": 1772335363000,
    "supported_hijri_date_codes": [
      "bgd",
      "fra",
      "idn",
      "ind",
      "jpn",
      "mys",
      "pak",
      "sau",
      "sgp",
      "aus",
      "deu",
      "rou"
    ]
  },
  {
    "name": "app_banner",
    "url": "appdata/data/{lang}/app_banner.json",
    "updated_at": 1773738603000
  },
  {
    "name": "home_cards",
    "url": "appdata/data/{lang}/home_cards.json",
    "updated_at": 1774062954000
  }
]
